README.md
setup.py
modules/pylap/__init__.py
modules/source/abso_bg.c
modules/source/dop_spread_eq.c
modules/source/ground_bs_loss.c
modules/source/ground_fs_loss.c
modules/source/igrf2007.c
modules/source/igrf2011.c
modules/source/igrf2016.c
modules/source/iri2007.c
modules/source/iri2012.c
modules/source/iri2016.c
modules/source/irreg_strength.c
modules/source/nrlmsise00.c
modules/source/raytrace_2d.c
modules/source/raytrace_2d_sp.c
modules/source/raytrace_3d.c
modules/source/raytrace_3d_sp.c
modules/source/common/check_ref_data.c
modules/source/common/numpy_to_double_1d.c
modules/source/common/parse_elev_freq.c
modules/source/common/parse_tol.c
modules/source/common/parse_ut.c
modules/source/common/stepmemcpyd.c
pylap.egg-info/PKG-INFO
pylap.egg-info/SOURCES.txt
pylap.egg-info/dependency_links.txt
pylap.egg-info/requires.txt
pylap.egg-info/top_level.txt