Metadata-Version: 1.0
Name: pylap
Version: 0.1.0a0
Summary: A numpy-compatible Python 3 wrapper for the PHaRLAP ionospheric raytracer
Home-page: UNKNOWN
Author: UNKNOWN
Author-email: UNKNOWN
License: UNKNOWN
Platform: UNKNOWN
